harmatz/__init__.py
harmatz-0.0.1.dist-info/LICENSE
harmatz-0.0.1.dist-info/METADATA
harmatz-0.0.1.dist-info/WHEEL
harmatz-0.0.1.dist-info/top_level.txt
harmatz-0.0.1.dist-info/RECORD
