Metadata-Version: 2.1
Name: harmatz
Version: 0.0.1
Summary: my python package
Home-page: https://github.com/yehonatanHarmatz/harmatz
Author: Yehonatan Harmatz
Author-email: harmatz.y@gmail.com
License: UNKNOWN
Project-URL: Bug Tracker, https://github.com/yehonatanHarmatz/harmatz/issues
Platform: UNKNOWN
Classifier: Programming Language :: Python :: 3
Classifier: License :: OSI Approved :: MIT License
Classifier: Operating System :: OS Independent
Requires-Python: >=3.6
